{
	"intents":[
		{
			"id": "0",
			"tag": "greetings",
			"user": [
				"hi", "hello", "hi there", "hey alina"
			],
			"type": "chat",
			"replies":[
				"Hi there", "Hello", "Hello @username, I'm Alina"
			],
			"mode": "chat"
		},
		{
			"id": "1",
			"tag": "languages",
			"user": [
				"what other languages can you speak", "can you speak hindi", "what languages can you understand"
			],
			"type": "chat",
			"replies":[
				"I can understand Hindi but I am still learning to speak it", "I can understand Hindi. Try saying something in Hindi to me."
			],
			"mode": "chat"
		},
		{
			"id": "2",
			"tag": "job",
			"user": [
				"what can you do", "what are your capabilities", "can you do something"
			],
			"type": "chat",
			"replies":[
				"Hello @username, I'm Alina. I can have a general conversation with you. I can even find you information on the internet. Or, if you are bored, I can play a few games with you."
			],
			"mode": "chat"
		},
		{
			"id": "3",
			"tag": "info",
			"user": [
				"who are you", "what is your name", "introduce yourself"
			],
			"type": "chat",
			"replies":[
				"Hi @username, I'm Alina", "Hello, I'm Alina", "Hello World, I'm Alina"
			],
			"mode": "chat"
		},
		{
			"id": "4",
			"tag": "health",
			"user": [
				"how are you", "whats up", "are you fine"
			],
			"type": "chat",
			"replies":[
				"I'm great, what about you @username?", "Awesome"
			],
			"mode": "chat"
		},
		{
			"id": "5",
			"tag": "time",
			"user": [
				"what is the time", "what time is it", "tell me the time", "time", "what's the time"
			],
			"type": "text-var",
			"replies":[
				"The current time is @time", "It's @time", "@time"
			],
			"mode": "chat"
		},
		{
			"id": "6",
			"tag": "bye",
			"user": [
				"bye", "see you later", "quit", "goodbye", "okay see you later", "got to go. see you later."
			],
			"type": "text-var",
			"replies":[
				"Good bye", "Bye, see you later", "See you later"
			],
			"mode": "chat"
		},
		{
			"id": "7",
			"tag": "sayhi",
			"user": [
				"say hi", "say hello", "say hi to", "say hello to", "greet"
			],
			"type": "chat",
			"replies":[
				"Hi there, I'm Alina", "Hello, I'm Alina", "Hi, I'm Alina. Pleasure to meeet you."
			],
			"mode": "chat"
		},
		{
			"id": "8",
			"tag": "wiki",
			"user": [
				"can you search wikipedia", "can you search wikipedia for me", "can you scan wikipedia for me"
			],
			"type": "chat",
			"replies":[
				"For you, anything", "Say 'Hey Alina, search wikipedia for something'.", "Try asking something"
			],
			"mode": "chat"
		},
		{
			"id": "9",
			"tag": "wiki",
			"user": [
				"who is", "what is the meaning", "what is", "what do you mean by", "search wikipedia for"
			],
			"type": "function",
			"replies":[
				"Searching Wikipedia", "Scanning Wikipedia"
			],
			"function": "fn.wiki('@q')",
			"mode": "chat"
		},
		{
			"id": "10",
			"tag": "game",
			"user": [
				"let's play a game", "i'm getting bored. let's play a game'", "i want to play a game", "what games are available", "what games can you play", "i want to play a game"
			],
			"type": "mode_changer",
			"replies":[
				"Currently I can play two games. Rock Paper and Scissors and Guess the Number.", "Which game do you want to play: Guess the Number or Rock Paper and Scissors"
			],
			"mode": "chat"
		},
		{
			"id": "11",
			"tag": "game",
			"user": [
				"let's play rock paper scissors", "start rock paper scissors", "rock paper scissors", "get in rock paper scissors mode"
			],
			"type": "mode_changer",
			"replies":[
				"Great! Let's Play Rock Paper Scissors. Say 'quit' to exit", "Get Ready! Let's Play Rock Paper Scissors. Say 'quit' to exit."
			],
			"mode": "rps"
		},
		{
			"id": "13",
			"tag": "calculator",
			"user": [
				"calculate", "multiply", "divide", "add", "subtract"
			],
			"type": "function",
			"replies":[
				"..."
			],
			"function": "fn.calculate('@q')",
			"mode": "chat"
		},
		{
			"id": "14",
			"tag": "downloader",
			"user": [
				"download video", "youtube video downloader", "download youtube video"
			],
			"type": "function",
			"replies":[
				"Getting your video"
			],
			"function": "fn.youtube('@q')",
			"mode": "chat"
		},
		{
			"id": "15",
			"tag": "google",
			"user": [
				"can you scan google", "can you search google", "can you google something"
			],
			"type": "chat",
			"replies":[
				"Just say", "Try saying 'Hey Alina, search google for something'", "For you, anything"
			],
			"mode": "chat"
		},
		{
			"id": "16",
			"tag": "google",
			"user": [
				"search google for", "open google"
			],
			"type": "function",
			"replies":[
				"Searching Wikipedia", "Scanning Wikipedia"
			],
			"function": "fn.google('@q')",
			"mode": "chat"
		},
		{
			"id": "120",
			"tag": "guess_the_number",
			"user": [
				"let's play guess the number", "start guess the number", "guess the number", "get in guess the number mode"
			],
			"type": "mode_changer",
			"replies":[
				"Great! Let's Play Guess the Number. Say 'quit' to exit", "Get Ready! Let's Play Guess the Number. Say 'quit' to exit."
			],
			"mode": "guessthenumber"
		}
	]
}